pyDHL/__init__.py
pyDHL/command_line.py
pyDHL/requests.py
pyDHL-0.3.dist-info/METADATA
pyDHL-0.3.dist-info/WHEEL
pyDHL-0.3.dist-info/entry_points.txt
pyDHL-0.3.dist-info/top_level.txt
pyDHL-0.3.dist-info/RECORD
