Metadata-Version: 2.1
Name: pyDHL
Version: 0.3
Summary: DHL REST Webservice integration
Home-page: UNKNOWN
Author: SMACH Team
Maintainer-email: pablo.riutort@smachteam.com
License: UNKNOWN
Platform: UNKNOWN
